madura_api/__init__.py
madura_api/main.py
madura_api-0.1.5.dist-info/LICENSE
madura_api-0.1.5.dist-info/METADATA
madura_api-0.1.5.dist-info/WHEEL
madura_api-0.1.5.dist-info/top_level.txt
madura_api-0.1.5.dist-info/RECORD
