Metadata-Version: 2.1
Name: madura-api
Version: 0.1.5
Summary: An API to access online madura dictionary
Home-page: https://github.com/nova9/madura_api
Author: nova9
Author-email: 
License: UNKNOWN
Project-URL: Bug Tracker, https://github.com/nova9/madura_api/issues
Platform: UNKNOWN
Classifier: Programming Language :: Python :: 3
Classifier: License :: OSI Approved :: GNU General Public License v3 (GPLv3)
Classifier: Operating System :: OS Independent
Requires-Python: >=3.6
License-File: LICENSE
Requires-Dist: requests
Requires-Dist: beautifulsoup4
Requires-Dist: lxml
